hooks/__init__.py
hooks/yeedu.py
operators/__init__.py
operators/yeedu.py
prefect_yeedu_operator-1.0.8.dist-info/METADATA
prefect_yeedu_operator-1.0.8.dist-info/WHEEL
prefect_yeedu_operator-1.0.8.dist-info/top_level.txt
prefect_yeedu_operator-1.0.8.dist-info/RECORD
