Metadata-Version: 2.1
Name: prefect-yeedu-operator
Version: 1.0.8
Summary: Submission and monitoring of jobs and notebooks using the Yeedu API in prefect. 
Author: Yeedu Admin
Author-email: yeedu_devops@yeedu.io
License: All Rights Reserved
Requires-Dist: requests >=2.27
Requires-Dist: websocket-client >=1.8.0
Requires-Dist: rel >=0.4.9.19
Requires-Dist: prefect-github ==0.2.6
Requires-Dist: prefect >=2.16.9
